ocmpy/__init__.py
ocmpy/base.py
ocmpy-0.1.4.dist-info/METADATA
ocmpy-0.1.4.dist-info/RECORD
ocmpy-0.1.4.dist-info/WHEEL
ocmpy-0.1.4.dist-info/top_level.txt
test/__init__.py
test/test_ocmpy.py
