Metadata-Version: 2.1
Name: ocmpy
Version: 0.1.4
Summary: Python API wrapper for the Open Charge Map for EV charging stations
Home-page: https://gitlab.com/loredous/ocmpy
Author: Jeremy Banker
Author-email: loredous@loredous.net
License: UNKNOWN
Platform: UNKNOWN
Classifier: Programming Language :: Python :: 3
Classifier: License :: OSI Approved :: GNU General Public License v3 (GPLv3)
Classifier: Operating System :: OS Independent
Requires-Dist: requests
